{
"title":"Dvanáctka",
"dataSources":[
  {
    "id":"dsRadNews",
    "title":"News",
    "title@cs":"Aktuality",
    "icon":"ds_news",
    "type":"news",
    "backgroundColor":"#884d3f"
  },
  {
    "id":"dsRadEvents",
    "title":"Events",
    "title@cs":"Akce",
    "icon":"ds_events",
    "type":"events",
    "backgroundColor":"#2d55db",
    "filterable":true
  },
  {
    "id":"dsRadDeska",
    "title":"Official Board",
    "title@cs":"Úřední deska",
    "icon":"ds_billboard",
    "type":"news",
    "backgroundColor":"#884d3f",
    "filterable":true,
    "listingSearchBarVisibleAtStart":true
  },
  {
    "id":"dsSpolky",
    "title":"Independent",
    "title@cs":"Nezávisle",
    "icon":"ds_magazine",
    "type":"news",
    "backgroundColor":"#9f7308",
    "filterable":true
  },
  {
    "id":"dsSpolkyList",
    "title":"Associations",
    "title@cs":"Spolky",
    "icon":"ds_usergroups",
    "type":"places",
    "backgroundColor":"#9f7308",
    "refreshFreqHours":48,
    "offlineJsonFile":"test_files/spolkyList"
  },
  {
    "id":"dsCityOffice",
    "title":"City Office",
    "title@cs":"Úřad",
    "icon":"ds_parliament",
    "type":"places",
    "backgroundColor":"#884d3f",
    "refreshFreqHours":100,
    "offlineJsonFile":"test_files/dyn_cityOffice",
    "filterAsParentView":true,
    "mapEnabled":false,
    "listingSearchBarVisibleAtStart":true
  },
  {
    "id":"dsBiografProgram",
    "title":"Modřanský biograf",
    "title@cs":"Program Modřanského biografu",
    "shortTitle":"Biograf",
    "icon":"ds_biograf",
    "type":"events",
    "backgroundColor":"#2d55db",
    "refreshFreqHours":48,
    "listingShowEventAddress":false
  },
  {
    "id":"dsCooltour",
    "title":"Trips",
    "title@cs":"Výlety",
    "icon":"ds_landmarks",
    "type":"places",
    "backgroundColor":"#008000",
    "refreshFreqHours":48,
    "offlineJsonFile":"test_files/p12kultpamatky"
  },
  {
    "id":"dsWaste",
    "title":"Waste",
    "title@cs":"Odpad",
    "icon":"ds_waste",
    "type":"places",
    "backgroundColor":"#008000",
    "refreshFreqHours":48,
    "offlineJsonFile":"test_files/dyn_waste",
    "filterAsParentView":true
  },
  {
    "id":"dsSosContacts",
    "title":"Help",
    "title@cs":"Pomoc",
    "icon":"ds_help",
    "type":"places",
    "backgroundColor":"#9f7308",
    "refreshFreqHours":48,
    "offlineJsonFile":"test_files/sos"
  },
  {
    "id":"dsReportFault",
    "title":"Report Fault",
    "title@cs":"Vyfotit závadu",
    "icon":"ds_reportfault",
    "type":"places",
    "backgroundColor":"#411ab1",
    "refreshFreqHours":1000
  },
  {
    "id":"dsGame",
    "title":"Game",
    "title@cs":"Hra",
    "icon":"ds_game",
    "type":"places",
    "backgroundColor":"#bb3c60",
    "refreshFreqHours":1000
  },
  {
    "id":"dsShops",
    "title":"Shops",
    "title@cs":"Firmy",
    "icon":"ds_shop",
    "type":"places",
    "backgroundColor":"#b2b20a",
    "refreshFreqHours":48,
    "offlineJsonFile":"test_files/p12shops",
    "filterAsParentView":true,
    "listingSearchBarVisibleAtStart":true
  },
  {
    "id":"dsWork",
    "title":"Work",
    "title@cs":"Práce",
    "icon":"ds_work",
    "type":"places",
    "backgroundColor":"#b2b20a",
    "listingFooterCustomLabelText":"Add job offer:",
    "listingFooterCustomLabelText@cs":"Přidat nabídku:",
    "listingFooterCustomButtonText":"KdeJePrace.cz",
    "listingFooterCustomButtonTargetUrl":"https://www.kdejeprace.cz/pridat?utm_source=dvanactka.info&utm_medium=app"
  },
  {
    "id":"dsTraffic",
    "title":"Traffic",
    "title@cs":"Doprava",
    "icon":"ds_roadblock",
    "type":"places",
    "backgroundColor":"#411ab1",
    "refreshFreqHours":4
  }
  ]
}